commandchat-0.0.11.dist-info/licenses/LICENSE
occ/CommandChat.py
occ/ConvertLogToMarkDown.py
occ/__init__.py
occ/command/__init__.py
occ/command/__main__.py
occ/commons/__init__.py
occ/commons/config.py
occ/configuration/__init__.py
occ/configuration/profile_config.py
occ/utils/CommonUtil.py
occ/utils/__init__.py
occ/utils/logger.py
commandchat-0.0.11.dist-info/METADATA
commandchat-0.0.11.dist-info/WHEEL
commandchat-0.0.11.dist-info/entry_points.txt
commandchat-0.0.11.dist-info/top_level.txt
commandchat-0.0.11.dist-info/RECORD
