Metadata-Version: 2.4
Name: commandchat
Version: 0.0.11
Summary: use command to chat with openai models
Home-page: https://github.com/
Author: xoto
Author-email: xoto <xxx.tao.c@gmail.com>
License: MIT
Project-URL: Homepage, https://github.com/xoto/commandchat
Classifier: Programming Language :: Python :: 3
Classifier: License :: OSI Approved :: MIT License
Classifier: Operating System :: OS Independent
Requires-Python: >=3.8
License-File: LICENSE
Requires-Dist: click
Requires-Dist: Image
Requires-Dist: openai
Requires-Dist: prompt_toolkit
Requires-Dist: rich
Dynamic: author
Dynamic: home-page
Dynamic: license-file
